lcm_tools/logtools/CMakeLists.txt
lcm_tools/logtools/img2log/README.md
lcm_tools/logtools/img2log/img2log.py
lcm_tools/logtools/imgt2img/imgt2img.py
lcm_tools/logtools/log2pkl/README.md
lcm_tools/logtools/log2pkl/lcmlog2smat/__init__.py
lcm_tools/logtools/log2pkl/lcmlog2smat/log_to_smat.py
lcm_tools/logtools/log2pkl/lcmlog2smat/scan_for_lcmtypes.py
lcm_tools/logtools/log2pkl/log2pkl.py
lcm_tools/logtools/requirements.txt
lcm_tools/misc/CMakeLists.txt
lcm_tools/misc/requirements.txt
lcm_tools/misc/winfrog/README.md
lcm_tools/misc/winfrog/tcp_simulator.py
lcm_tools/misc/winfrog/usbl_republisher.py
lcm_tools/republishers/CMakeLists.txt
lcm_tools/republishers/calibrated_ahrs/README.md
lcm_tools/republishers/calibrated_ahrs/corrected_ahrs.py
lcm_tools/republishers/config/config_ahrs_calibration.json
lcm_tools/republishers/lass_republisher/README.md
lcm_tools/republishers/lass_republisher/ins_republisher.py
lcm_tools/republishers/lass_republisher/lass_republisher_bot_core/__init__.py
lcm_tools/republishers/lass_republisher/lass_republisher_bot_core/image_metadata_t.py
lcm_tools/republishers/lass_republisher/lass_republisher_bot_core/image_sync_t.py
lcm_tools/republishers/lass_republisher/lass_republisher_bot_core/image_t.py
lcm_tools/republishers/lass_republisher/lass_republisher_bot_core/raw_t.py
lcm_tools/republishers/lass_republisher/lass_republisher_oi/__init__.py
lcm_tools/republishers/lass_republisher/lass_republisher_oi/double_t.py
lcm_tools/republishers/lass_republisher/lass_republisher_oi/kearfott_t.py
lcm_tools/republishers/lass_republisher/lass_republisher_oi/lcm_header_t.py
lcm_tools/republishers/lass_republisher/lass_republisher_oi/octans_t.py
lcm_tools/republishers/lass_republisher/lass_republisher_oi/rdi_pd4_t.py
lcm_tools/republishers/lass_republisher/prosilica_republisher.py
lcm_tools/republishers/requirements.txt
lcm_tools/sync/CMakeLists.txt
lcm_tools/sync/README.md
lcm_tools/sync/heartbeat.py
lcm_tools/sync/requirements.txt
compas_tools_lcm-0.1.0.dist-info/METADATA
compas_tools_lcm-0.1.0.dist-info/WHEEL
compas_tools_lcm-0.1.0.dist-info/entry_points.txt
compas_tools_lcm-0.1.0.dist-info/RECORD
