Metadata-Version: 2.1
Name: compas-tools-lcm
Version: 0.1.0
Summary: MBARI CoMPAS Lab executables for working with LCM data
Author: MBARI CoMPAS Lab
Requires-Python: >=3.8,<4.0
Classifier: Programming Language :: Python :: 3
Classifier: Programming Language :: Python :: 3.8
Classifier: Programming Language :: Python :: 3.9
Classifier: Programming Language :: Python :: 3.10
Classifier: Programming Language :: Python :: 3.11
Requires-Dist: lcm (>=1.4.4,<2.0.0)
Requires-Dist: navlib (>=0.1.4,<0.2.0)
Requires-Dist: numpy (>=1.23,<2.0)
